cognac/__init__.py
cognac/core/BaseEnv.py
cognac/core/BaseReward.py
cognac/core/__init__.py
cognac/env/__init__.py
cognac/env/BinaryConsensus/__init__.py
cognac/env/BinaryConsensus/env.py
cognac/env/BinaryConsensus/rewards.py
cognac/env/FirefightingGraph/__init__.py
cognac/env/FirefightingGraph/env.py
cognac/env/FirefightingGraph/rewards.py
cognac/env/MultiCommodityFlow/__init__.py
cognac/env/MultiCommodityFlow/env.py
cognac/env/MultiCommodityFlow/rewards.py
cognac/env/SysAdmin/__init__.py
cognac/env/SysAdmin/env.py
cognac/env/SysAdmin/rewards.py
cognac/utils/__init__.py
cognac/utils/graph_utils.py
cognac/utils/make_env.py
cognac/utils/visualization.py
cognac-0.1.8.dist-info/licenses/LICENSE.txt
cognac-0.1.8.dist-info/METADATA
cognac-0.1.8.dist-info/WHEEL
cognac-0.1.8.dist-info/top_level.txt
cognac-0.1.8.dist-info/RECORD
