Metadata-Version: 2.4
Name: cognac
Version: 0.1.8
Summary: Cooperative Graph-based Networked Agent Challenges for Multi-Agent Reinforcement Learning.
Author-email: Jules Sintes <jules.sintes@inria.fr>
License-Expression: Apache-2.0
Project-URL: Homepage, https://github.com/yojul/cognac#
Project-URL: Issues, https://github.com/yojul/cognac/issues
Classifier: Programming Language :: Python :: 3
Classifier: Operating System :: OS Independent
Requires-Python: >=3.12
License-File: LICENSE.txt
Requires-Dist: gymnasium>=1.0.0
Requires-Dist: numpy>=2.1.3
Requires-Dist: matplotlib>=3.0
Requires-Dist: pettingzoo>=1.24
Requires-Dist: networkx>=3.4
Requires-Dist: imageio>=2.37
Provides-Extra: docs
Requires-Dist: sphinx; extra == "docs"
Requires-Dist: sphinx_rtd_theme; extra == "docs"
Requires-Dist: sphinxcontrib-bibtex; extra == "docs"
Dynamic: license-file
